{
  "composite_A": {
    "groups": {
      "top": "triangle_C",
      "bottom": "triangle_C",
      "mask": "circle_C"
    },
    "mode": "single",
    "group_mode": "A"
  },
  "composite_B": {
    "groups": {
      "top": "triangle_C",
      "bottom": "triangle_C",
      "mask": "circle_B"
    },
    "mode": "single",
    "group_mode": "B"
  },
  "composite_C": {
    "groups": {
      "top": "triangle_C",
      "bottom": "triangle_C",
      "mask": "circle_B"
    },
    "mode": "group",
    "group_mode": "A"
  }
}
